tabler_icons/__init__.py
tabler_icons/cli.py
tabler_icons/utils.py
tabler_icons/management/__init__.py
tabler_icons/management/commands/__init__.py
tabler_icons/management/commands/download_icons.py
tabler_icons/templatetags/__init__.py
tabler_icons/templatetags/tabler_icons.py
django_tabler_icons-0.7.2.dist-info/METADATA
django_tabler_icons-0.7.2.dist-info/WHEEL
django_tabler_icons-0.7.2.dist-info/entry_points.txt
django_tabler_icons-0.7.2.dist-info/top_level.txt
django_tabler_icons-0.7.2.dist-info/RECORD
