Metadata-Version: 2.4
Name: django-tabler-icons
Version: 0.7.2
Summary: Use tabler icons with django templates
Author: Demetris Stavrou
Project-URL: Repository, https://github.com/demestav/django_tabler_icons
Classifier: Development Status :: 5 - Production/Stable
Classifier: Intended Audience :: Developers
Classifier: Programming Language :: Python :: 3 :: Only
Classifier: Programming Language :: Python :: 3.9
Classifier: Programming Language :: Python :: 3.10
Classifier: Programming Language :: Python :: 3.11
Classifier: Programming Language :: Python :: 3.12
Classifier: Programming Language :: Python :: 3.13
Requires-Python: >=3.9
Requires-Dist: django>4.2
